{
    "completions": [
        {
            "id": 2001,
            "lead_time": 26.3,
            "result": [
                {
                    "from_name": "tag",
                    "id": "XifNGcRyjr",
                    "original_height": 511,
                    "original_width": 768,
                    "source": "$image",
                    "to_name": "img",
                    "type": "polygonlabels",
                    "value": {
                        "points": [
                            [
                                23.733333333333334,
                                55.31062124248498
                            ],
                            [
                                27.333333333333332,
                                55.91182364729458
                            ],
                            [
                                28.8,
                                52.30460921843687
                            ],
                            [
                                29.333333333333332,
                                47.494989979959925
                            ],
                            [
                                28.8,
                                42.68537074148296
                            ],
                            [
                                29.86666666666667,
                                40.480961923847694
                            ],
                            [
                                28.933333333333334,
                                35.87174348697395
                            ],
                            [
                                26.933333333333337,
                                38.276553106212425
                            ],
                            [
                                26.133333333333336,
                                39.879759519038075
                            ],
                            [
                                23.333333333333332,
                                44.08817635270542
                            ],
                            [
                                21.46666666666667,
                                47.69539078156313
                            ],
                            [
                                17.866666666666667,
                                49.09819639278557
                            ],
                            [
                                16.666666666666668,
                                47.0941883767535
                            ],
                            [
                                16.533333333333335,
                                43.08617234468939
                            ],
                            [
                                18.133333333333336,
                                41.28256513026052
                            ],
                            [
                                20.133333333333333,
                                39.879759519038075
                            ],
                            [
                                22.400000000000002,
                                33.86773547094189
                            ],
                            [
                                24.8,
                                30.66132264529058
                            ],
                            [
                                26.266666666666666,
                                27.454909819639276
                            ],
                            [
                                28.8,
                                23.647294589178358
                            ],
                            [
                                31.466666666666665,
                                21.24248496993988
                            ],
                            [
                                31.466666666666665,
                                20.04008016032064
                            ],
                            [
                                31.333333333333332,
                                15.030060120240483
                            ],
                            [
                                35.06666666666667,
                                10.220440881763528
                            ],
                            [
                                38.266666666666666,
                                10.821643286573147
                            ],
                            [
                                38.8,
                                13.827655310621244
                            ],
                            [
                                39.86666666666667,
                                20.440881763527056
                            ],
                            [
                                43.06666666666667,
                                20.04008016032064
                            ],
                            [
                                46.133333333333326,
                                21.442885771543086
                            ],
                            [
                                50,
                                21.643286573146295
                            ],
                            [
                                53.20000000000001,
                                19.839679358717436
                            ],
                            [
                                56.53333333333333,
                                17.034068136272545
                            ],
                            [
                                58.4,
                                15.6312625250501
                            ],
                            [
                                59.199999999999996,
                                17.43486973947896
                            ],
                            [
                                58.4,
                                21.24248496993988
                            ],
                            [
                                55.46666666666667,
                                22.84569138276553
                            ],
                            [
                                53.46666666666667,
                                25.65130260521042
                            ],
                            [
                                49.73333333333333,
                                28.0561122244489
                            ],
                            [
                                43.86666666666667,
                                31.062124248496996
                            ],
                            [
                                42.13333333333333,
                                34.4689378757515
                            ],
                            [
                                43.199999999999996,
                                39.879759519038075
                            ],
                            [
                                43.46666666666667,
                                46.492985971943895
                            ],
                            [
                                43.73333333333334,
                                52.50501002004008
                            ],
                            [
                                44.26666666666667,
                                59.519038076152306
                            ],
                            [
                                44.26666666666667,
                                65.33066132264528
                            ],
                            [
                                43.06666666666667,
                                70.54108216432867
                            ],
                            [
                                42.4,
                                73.74749498997996
                            ],
                            [
                                41.733333333333334,
                                78.15631262525051
                            ],
                            [
                                41.46666666666667,
                                80.36072144288578
                            ],
                            [
                                38.93333333333333,
                                81.96392785571142
                            ],
                            [
                                36.800000000000004,
                                82.16432865731464
                            ],
                            [
                                33.6,
                                82.56513026052104
                            ],
                            [
                                33.06666666666667,
                                78.15631262525051
                            ],
                            [
                                34.266666666666666,
                                73.54709418837676
                            ],
                            [
                                34.666666666666664,
                                69.13827655310622
                            ],
                            [
                                34.93333333333334,
                                65.13026052104209
                            ],
                            [
                                34.13333333333333,
                                59.71943887775552
                            ],
                            [
                                32,
                                61.92384769539079
                            ],
                            [
                                30.266666666666666,
                                63.52705410821643
                            ],
                            [
                                26.8,
                                64.32865731462927
                            ],
                            [
                                22.666666666666668,
                                65.13026052104209
                            ],
                            [
                                21.2,
                                66.33266533066134
                            ],
                            [
                                16.266666666666666,
                                67.93587174348698
                            ],
                            [
                                14.266666666666666,
                                67.53507014028055
                            ],
                            [
                                14,
                                61.92384769539079
                            ],
                            [
                                15.200000000000001,
                                58.517034068136276
                            ],
                            [
                                18.133333333333336,
                                55.31062124248498
                            ],
                            [
                                21.2,
                                53.90781563126252
                            ]
                        ],
                        "polygonlabels": [
                            "Manusia"
                        ]
                    }
                }
            ]
        }
    ],
    "data": {
        "image": "http://data.heartex.net/open-images/train_6/mini/699778bbff222b98.jpg"
    },
    "id": 2
}